backtester_agent/__init__.py
backtester_agent/main.py
backtester_agent-0.0.2.dist-info/LICENSE
backtester_agent-0.0.2.dist-info/METADATA
backtester_agent-0.0.2.dist-info/WHEEL
backtester_agent-0.0.2.dist-info/RECORD
